odoo/addons/product_sale_description/README.rst
odoo/addons/product_sale_description/__init__.py
odoo/addons/product_sale_description/__manifest__.py
odoo/addons/product_sale_description/i18n/es.po
odoo/addons/product_sale_description/i18n/it.po
odoo/addons/product_sale_description/i18n/product_sale_description.pot
odoo/addons/product_sale_description/i18n/tr.po
odoo/addons/product_sale_description/models/__init__.py
odoo/addons/product_sale_description/models/product_template.py
odoo/addons/product_sale_description/readme/CONTRIBUTORS.rst
odoo/addons/product_sale_description/readme/DESCRIPTION.rst
odoo/addons/product_sale_description/static/description/icon.png
odoo/addons/product_sale_description/static/description/index.html
odoo/addons/product_sale_description/views/product_template.xml
odoo_addon_product_sale_description-16.0.1.0.1.7.dist-info/METADATA
odoo_addon_product_sale_description-16.0.1.0.1.7.dist-info/WHEEL
odoo_addon_product_sale_description-16.0.1.0.1.7.dist-info/top_level.txt
odoo_addon_product_sale_description-16.0.1.0.1.7.dist-info/RECORD
